Metadata-Version: 2.4
Name: flippy-lang
Version: 0.1.4
Summary: FlipPy probabilistic programming language
License-File: LICENSE
Provides-Extra: dev
Requires-Dist: pytest; extra == "dev"
Requires-Dist: flake8; extra == "dev"
Requires-Dist: twine; extra == "dev"
Requires-Dist: build; extra == "dev"
Requires-Dist: pdoc==15.0.3; extra == "dev"
Requires-Dist: jupyter==1.1.1; extra == "dev"
Provides-Extra: full
Requires-Dist: joblib==1.4.2; extra == "full"
Requires-Dist: numpy==2.0.2; extra == "full"
Requires-Dist: scipy==1.14.1; extra == "full"
Requires-Dist: sympy~=1.13.3; extra == "full"
Requires-Dist: matplotlib==3.10.3; extra == "full"
Requires-Dist: pandas==2.3.1; extra == "full"
Requires-Dist: seaborn==0.13.2; extra == "full"
Dynamic: license-file
